.gitignore
README
TODO
env.sh
run.sh
setup.py
pagingish/__init__.py
pagingish/couchdbpager.py
pagingish/genericpager.py
pagingish/listpager.py
pagingish/webpaging.py
pagingish.egg-info/PKG-INFO
pagingish.egg-info/SOURCES.txt
pagingish.egg-info/dependency_links.txt
pagingish.egg-info/entry_points.txt
pagingish.egg-info/top_level.txt
pagingish.egg-info/zip-safe
pagingish/templates/paging.css
pagingish/templates/mako/paging.html
pagingish/tests/TODO
pagingish/tests/createdata.py
pagingish/tests/test_couchdbpager.py
pagingish/tests/test_couchdbskiplimitpager.py
pagingish/tests/test_generic.py
pagingish/tests/test_listpager.py