Metadata-Version: 1.0
Name: pagingish
Version: 0.1
Summary:  Generic paging library - includes couchdb paging
Home-page: http://ish.io
Author: Tim Parkin & Matt Goodall
Author-email: info@timparkin.co.uk
License: UNKNOWN
Platform: UNKNOWN
